chinese_stock_mcp/__init__.py
chinese_stock_mcp/server.py
chinese_stock_mcp-0.1.1.dist-info/METADATA
chinese_stock_mcp-0.1.1.dist-info/WHEEL
chinese_stock_mcp-0.1.1.dist-info/entry_points.txt
chinese_stock_mcp-0.1.1.dist-info/top_level.txt
chinese_stock_mcp-0.1.1.dist-info/RECORD
