Metadata-Version: 2.4
Name: chinese-stock-mcp
Version: 0.1.1
Summary: Add your description here
Requires-Python: >=3.10
Requires-Dist: fastmcp>=2.10.5
Requires-Dist: pysnowball>=0.1.5
